MANIFEST.in
README.md
setup.py
rho_web/__init__.py
rho_web/helpers.py
rho_web/json.py
rho_web/response.py
rho_web/restful.py
rho_web/smorest.py
rho_web.egg-info/PKG-INFO
rho_web.egg-info/SOURCES.txt
rho_web.egg-info/dependency_links.txt
rho_web.egg-info/requires.txt
rho_web.egg-info/top_level.txt