Metadata-Version: 2.1
Name: rho-web
Version: 0.3.4
Summary: Contains common utilities for web development
Home-page: https://bitbucket.org/rhoai/rho-web
Maintainer: Rho AI Corporation
License: Commercial
Platform: UNKNOWN
Provides-Extra: dev
Provides-Extra: smorest
